productsup_py/__init__.py
productsup_py/__version__.py
productsup_py/auth.py
productsup_py/models.py
productsup_py/projects.py
productsup_py/sites.py
productsup_py/errors/__init__.py
productsup_py/errors/productup_exception.py
productsup_py-0.0.1.dist-info/LICENSE
productsup_py-0.0.1.dist-info/METADATA
productsup_py-0.0.1.dist-info/WHEEL
productsup_py-0.0.1.dist-info/top_level.txt
productsup_py-0.0.1.dist-info/RECORD
