Metadata-Version: 2.1
Name: productsup-py
Version: 0.0.1
Summary: A Python wrapper for the ProductsUp API
Home-page: https://github.com/lyestarzalt/ProductsUp_py
Author: Lyes Tarzalt
Author-email: lyestarzalt@gmail.com
Classifier: License :: OSI Approved :: BSD License
Classifier: Intended Audience :: Developers
Classifier: Programming Language :: Python :: 3.7
License-File: LICENSE
Requires-Dist: requests
